cubicweb_rememberme/__init__.py
cubicweb_rememberme/__pkginfo__.py
cubicweb_rememberme/authplugin.py
cubicweb_rememberme/hooks.py
cubicweb_rememberme/schema.py
cubicweb_rememberme/site_cubicweb.py
cubicweb_rememberme/views.py
cubicweb_rememberme/i18n/en.po
cubicweb_rememberme/i18n/fr.po
cubicweb_rememberme/migration/1.0.0_Any.py
cubicweb_rememberme/wdoc/ChangeLog_en
cubicweb_rememberme/wdoc/ChangeLog_fr
cubicweb_rememberme-1.2.0.dist-info/METADATA
cubicweb_rememberme-1.2.0.dist-info/WHEEL
cubicweb_rememberme-1.2.0.dist-info/entry_points.txt
cubicweb_rememberme-1.2.0.dist-info/top_level.txt
cubicweb_rememberme-1.2.0.dist-info/RECORD
